sciqlopplots-0.18.0.dist-info/METADATA
sciqlopplots-0.18.0.dist-info/WHEEL
sciqlopplots-0.18.0.dist-info/COPYING
SciQLopPlots/SciQLopPlotsBindings.cp313-win_amd64.pyd
SciQLopPlots/__init__.py
sciqlopplots-0.18.0.dist-info/RECORD
