Metadata-Version: 2.1
Name: SciQLopPlots
Version: 0.18.0
Summary: SciQLop plot API based on QCustomPlot
Author-Email: Alexis Jeandet <alexis.jeandet@member.fsf.org>
License: GNU GENERAL PUBLIC LICENSE
Classifier: Development Status :: 4 - Beta
Classifier: Intended Audience :: Developers
Classifier: License :: OSI Approved :: GNU General Public License v3 (GPLv3)
Classifier: Natural Language :: English
Classifier: Programming Language :: Python :: 3
Classifier: Programming Language :: Python :: 3.10
Classifier: Programming Language :: Python :: 3.11
Classifier: Programming Language :: Python :: 3.12
Classifier: Programming Language :: Python :: 3.13
Project-URL: homepage, https://github.com/SciQLop/SciQLopPlots
Requires-Python: >=3.9
Requires-Dist: numpy
Requires-Dist: pyside6==6.9.2
Requires-Dist: shiboken6==6.9.2
